{
    "openapi": "3.0.0",
    "info": {
        "title": "Role API",
        "description": "Laravel 13 Role + Pivot API with Swagger",
        "version": "1.0.0"
    },
    "servers": [
        {
            "url": "http://127.0.0.1:8000",
            "description": "Local server"
        }
    ],
    "paths": {
        "/api/test": {
            "get": {
                "tags": [
                    "Test"
                ],
                "summary": "Test endpoint",
                "operationId": "7a09caa81b6dfd4c5087d06d7689eaa8",
                "responses": {
                    "200": {
                        "description": "Success"
                    }
                }
            }
        }
    },
    "components": {
        "securitySchemes": {
            "bearerAuth": {
                "type": "http",
                "bearerFormat": "JWT",
                "scheme": "bearer"
            }
        }
    },
    "tags": [
        {
            "name": "Test",
            "description": "Test"
        }
    ]
}